[
  {
    "model": "users.customer",
    "pk": 2,
    "fields": {
      "user_id": "8a52869d034e4044a7d93da18f6b7e5d",
      "created_at": "2022-12-02 14:22:52.562348",
      "updated_at": "2022-12-02 14:22:52.562348",
      "is_verified": true,
      "image": "user_profile/example_photo.png",
      "company_name": "Richter Supermarkt",
      "contact_name": "Michael Holz",
      "contact_title": "Sales Manager",
      "address": "Grenzacherweg 237",
      "city": "Geneve",
      "region": null,
      "postal_code": "1203",
      "country": "Switzerland",
      "phone": "0897-034214",
      "fax": null
    }
  },
  {
    "model": "users.customer",
    "pk": 3,
    "fields": {
      "user_id": "2051e40555c946d1b00ad7060cfe0511",
      "created_at": "2022-12-02 14:22:52.562348",
      "updated_at": "2022-12-02 14:22:52.562348",
      "is_verified": true,
      "image": "user_profile/example_photo.png",
      "company_name": "White Clover Markets",
      "contact_name": "Karl Jablonski",
      "contact_title": "Owner",
      "address": "305 - 14th Ave. S. Suite 3B",
      "city": "Seattle",
      "region": "Seattle",
      "postal_code": "98128",
      "country": "USA",
      "phone": "(206) 555-4112",
      "fax": "(206) 555-4115"
    }
  },
  {
    "model": "users.customer",
    "pk": 4,
    "fields": {
      "user_id": "55b0c7d4c2d34ed38aca1bbcb07912c0",
      "created_at": "2022-12-02 14:22:52.562348",
      "updated_at": "2022-12-02 14:22:52.562348",
      "is_verified": true,
      "image": "user_profile/example_photo.png",
      "company_name": "Tortuga Restaurante",
      "contact_name": "Miguel Angel Paolino",
      "contact_title": "Owner",
      "address": "Avda. Azteca 123",
      "city": "Mexico D.F.",
      "region": null,
      "postal_code": "05033",
      "country": "Mexico",
      "phone": "(5) 555-2933",
      "fax": null
    }
  }
]