[
{
  "model": "auth.group",
  "pk": 1,
  "fields": {
    "name": "ExtraStaff",
    "permissions": [
      21,
      22,
      24,
      37,
      38,
      39,
      40,
      41,
      42,
      43,
      44,
      61,
      62,
      63,
      64,
      49,
      50,
      52,
      53,
      54,
      56,
      57,
      58,
      60,
      73,
      74,
      75,
      76,
      69,
      70,
      71,
      72,
      65,
      66,
      68
    ]
  }
},
{
  "model": "auth.group",
  "pk": 2,
  "fields": {
    "name": "Employee",
    "permissions": [
      21,
      24,
      37,
      38,
      39,
      40,
      41,
      42,
      43,
      44,
      61,
      62,
      64,
      72,
      68
    ]
  }
},
{
  "model": "auth.group",
  "pk": 3,
  "fields": {
    "name": "Customer",
    "permissions": [
      24,
      41,
      42,
      43,
      44,
      64
    ]
  }
}
]
